aiomonobank/__init__.py
aiomonobank/api.py
aiomonobank/base.py
aiomonobank/monobank.py
aiomonobank/types/__init__.py
aiomonobank/types/account.py
aiomonobank/types/client_info.py
aiomonobank/types/currency.py
aiomonobank/types/jar.py
aiomonobank/types/statement_item.py
aiomonobank/types/webhook_data.py
aiomonobank/utils/__init__.py
aiomonobank/utils/exceptions.py
aiomonobank-1.0.2.dist-info/METADATA
aiomonobank-1.0.2.dist-info/WHEEL
aiomonobank-1.0.2.dist-info/licenses/LICENSE
aiomonobank-1.0.2.dist-info/RECORD
