Metadata-Version: 2.1
Name: aiomonobank
Version: 1.0.2
Summary: Asynchronous Python library for monobank API
Project-URL: Homepage, https://github.com/TT1410/aiomonobank
Project-URL: Documentation, https://github.com/TT1410/aiomonobank
Project-URL: Repository, https://github.com/TT1410/aiomonobank
Author-email: TT1410 <taras@plaksii.cf>
Maintainer-email: TT1410 <taras@plaksii.cf>
License-File: LICENSE
Keywords: api,asyncio,bank,library,monobank,wrapper
Classifier: Development Status :: 5 - Production/Stable
Classifier: Environment :: Console
Classifier: Framework :: AsyncIO
Classifier: Intended Audience :: Developers
Classifier: Intended Audience :: System Administrators
Classifier: License :: OSI Approved :: MIT License
Classifier: Programming Language :: Python :: 3.10
Classifier: Programming Language :: Python :: 3.11
Classifier: Programming Language :: Python :: Implementation :: PyPy
Classifier: Topic :: Communications :: Chat
Classifier: Topic :: Software Development :: Libraries :: Python Modules
Classifier: Typing :: Typed
Requires-Python: >=3.10
Requires-Dist: aiocache>=0.12.1
Requires-Dist: aiohttp~=3.8.4
Requires-Dist: certifi>=2022.12.7
Requires-Dist: pydantic~=1.10.7
Requires-Dist: pytz>=2023.3
